LICENSE
MANIFEST.in
README.md
lektor_markdown_excerpt.py
setup.py
lektor_markdown_excerpt.egg-info/PKG-INFO
lektor_markdown_excerpt.egg-info/SOURCES.txt
lektor_markdown_excerpt.egg-info/dependency_links.txt
lektor_markdown_excerpt.egg-info/entry_points.txt
lektor_markdown_excerpt.egg-info/top_level.txt