Metadata-Version: 1.0
Name: lektor-markdown-excerpt
Version: 0.1
Summary: Adds filter for Markdown body excerpt.
Home-page: http://github.com/bancek/lektor-markdown-excerpt
Author: Luka Zakrajsek
Author-email: luka@bancek.net
License: BSD
Platform: UNKNOWN
